{
	"id": "3bf6a642-7efd-416e-a368-2b6ef5b375c7",
	"name": "CalculEat-ENV-PROD",
	"values": [
		{
			"key": "id_token",
			"value": "",
			"type": "secret",
			"enabled": true
		},
		{
			"key": "hostname",
			"value": "hostname",
			"type": "default",
			"enabled": true
		},
		{
			"key": "scheme",
			"value": "http",
			"type": "default",
			"enabled": true
		}
	],
	"_postman_variable_scope": "environment",
	"_postman_exported_at": "2023-09-30T11:07:04.133Z",
	"_postman_exported_using": "Postman/10.18.9"
}